cyroot/vector_bracketing.pyx
cyroot/vector_quasi_newton.cpp
cyroot/_defaults.py
cyroot/return_types.cpp
cyroot/vector_newton.cpython-36m-x86_64-linux-gnu.so
cyroot/_check_args.pyx
cyroot/__init__.pxd
cyroot/return_types.pyx
cyroot/scalar_root.py
cyroot/_check_args.cpython-36m-x86_64-linux-gnu.so
cyroot/vector_quasi_newton.pyx
cyroot/scalar_bracketing.pyx
cyroot/vector_derivative_approximation.cpp
cyroot/vector_derivative_approximation.pyx
cyroot/vector_derivative_approximation.pxd
cyroot/_check_args.pxd
cyroot/fptr.pyx
cyroot/vector_bracketing.cpp
cyroot/_version.py
cyroot/scalar_derivative_approximation.cpp
cyroot/return_types.cpython-36m-x86_64-linux-gnu.so
cyroot/fptr.cpython-36m-x86_64-linux-gnu.so
cyroot/scalar_derivative_approximation.pxd
cyroot/return_types.pxd
cyroot/scalar_newton.cpython-36m-x86_64-linux-gnu.so
cyroot/__init__.py
cyroot/scalar_bracketing.cpp
cyroot/fptr.cpp
cyroot/scalar_quasi_newton.pyx
cyroot/vector_bracketing.cpython-36m-x86_64-linux-gnu.so
cyroot/vector_newton.cpp
cyroot/vector_newton.pyx
cyroot/scalar_derivative_approximation.cpython-36m-x86_64-linux-gnu.so
cyroot/vector_root.py
cyroot/scalar_derivative_approximation.pyx
cyroot/_check_args.cpp
cyroot/scalar_newton.cpp
cyroot/vector_quasi_newton.cpython-36m-x86_64-linux-gnu.so
cyroot/scalar_bracketing.cpython-36m-x86_64-linux-gnu.so
cyroot/fptr.pxd
cyroot/scalar_newton.pyx
cyroot/_types.py
cyroot/scalar_quasi_newton.cpython-36m-x86_64-linux-gnu.so
cyroot/vector_derivative_approximation.cpython-36m-x86_64-linux-gnu.so
cyroot/scalar_quasi_newton.cpp
cyroot/utils/__init__.pxd
cyroot/utils/itertools.pxd
cyroot/utils/itertools.cpython-36m-x86_64-linux-gnu.so
cyroot/utils/itertools.cpp
cyroot/utils/_warnings.py
cyroot/utils/__init__.py
cyroot/utils/_function_registering.py
cyroot/utils/itertools.pyx
cyroot/ops/scalar_ops.cpython-36m-x86_64-linux-gnu.so
cyroot/ops/matrix_ops.pyx
cyroot/ops/matrix_ops.pxd
cyroot/ops/__init__.pxd
cy_root-1.0.3.dist-info/RECORD
cy_root-1.0.3.dist-info/WHEEL
cy_root-1.0.3.dist-info/LICENSE.txt
cy_root-1.0.3.dist-info/top_level.txt
cy_root-1.0.3.dist-info/METADATA
