Metadata-Version: 2.1
Name: cy-root
Version: 1.0.3
Summary: Cython implementations of multiple root-finding methods.
Home-page: https://github.com/inspiros/cy-root
Author: Hoang-Nhat Tran (inspiros)
Author-email: hnhat.tran@gmail.com
License: MIT
Project-URL: Source, https://github.com/inspiros/cy-root
Keywords: root-finding
Platform: UNKNOWN
Classifier: Development Status :: 3 - Alpha
Classifier: Intended Audience :: Developers
Classifier: Intended Audience :: Education
Classifier: Intended Audience :: Science/Research
Classifier: License :: OSI Approved :: MIT License
Classifier: Programming Language :: Python
Classifier: Programming Language :: Python :: 3
Classifier: Programming Language :: Python :: 3.6
Classifier: Programming Language :: Python :: 3.7
Classifier: Programming Language :: Python :: 3.8
Classifier: Programming Language :: Python :: 3.9
Classifier: Programming Language :: Python :: 3.10
Classifier: Programming Language :: Python :: 3.11
Classifier: Programming Language :: Cython
Classifier: Operating System :: OS Independent
Classifier: Topic :: Scientific/Engineering :: Mathematics
Requires-Python: >=3.6
License-File: LICENSE.txt
Requires-Dist: dynamic-default-args
Requires-Dist: numpy
Requires-Dist: scipy
Requires-Dist: sympy
Provides-Extra: dev
Requires-Dist: cython ; extra == 'dev'
Provides-Extra: examples
Requires-Dist: tqdm ; extra == 'examples'
